pytest_blame.py
tests/__init__.py
tests/conftest.py
tests/test_blame.py
tests/test_conftest.py
tests/test_sample.py
pytest_blame-0.1.7.dist-info/LICENSE
pytest_blame-0.1.7.dist-info/METADATA
pytest_blame-0.1.7.dist-info/WHEEL
pytest_blame-0.1.7.dist-info/entry_points.txt
pytest_blame-0.1.7.dist-info/top_level.txt
pytest_blame-0.1.7.dist-info/RECORD
