Metadata-Version: 2.1
Name: pytest-blame
Version: 0.1.7
Summary: A pytest plugin helps developers to debug by providing useful commits history.
Home-page: https://github.com/inTestiGator/pytest-blame
Author: Lancaster Wu, Spencer Huang, Carson Quigley, Patrick Palad, Paul Livingston
Author-email: wuj@allegheny.edu, huangs@allegheny.edu, quigleyc@allegheny.edu, paladp@allegheny.edu, livingstonp@allegheny.edu
License: GNU
Platform: any
Requires-Dist: pygithub
Requires-Dist: pytest (>=4.4.0)
Requires-Dist: gitpython
Requires-Dist: requests
